animations/__init__.py
animations/animations.py
common/__init__.py
common/common_functionalities.py
coordsim/__init__.py
coordsim/main.py
coordsim/controller/__init__.py
coordsim/controller/base_controller.py
coordsim/controller/duration_controller.py
coordsim/controller/flow_controller.py
coordsim/decision_maker/__init__.py
coordsim/decision_maker/base_decision_maker.py
coordsim/decision_maker/default_decision_maker.py
coordsim/decision_maker/external_decision_maker.py
coordsim/flow_generators/__init__.py
coordsim/flow_generators/base_generator.py
coordsim/flow_generators/default_generator.py
coordsim/flow_generators/list_generator.py
coordsim/flow_processors/__init__.py
coordsim/flow_processors/base_processor.py
coordsim/flow_processors/default_processor.py
coordsim/forwarders/__init__.py
coordsim/forwarders/base_forwarder.py
coordsim/forwarders/default_forwarder.py
coordsim/metrics/__init__.py
coordsim/metrics/metrics.py
coordsim/network/__init__.py
coordsim/network/dummy_data.py
coordsim/network/flow.py
coordsim/reader/__init__.py
coordsim/reader/reader.py
coordsim/simulation/__init__.py
coordsim/simulation/flowsimulator.py
coordsim/simulation/simulatorparams.py
coordsim/trace_processor/__init__.py
coordsim/trace_processor/trace_processor.py
coordsim/traffic_predictor/__init__.py
coordsim/traffic_predictor/lstm_predictor.py
coordsim/traffic_predictor/traffic_predictor.py
coordsim/writer/__init__.py
coordsim/writer/writer.py
dummy_env/__init__.py
dummy_env/dummy_simulator.py
siminterface/__init__.py
siminterface/simulator.py
spinterface/__init__.py
spinterface/spinterface.py
coord_sim-2.2.1.dist-info/METADATA
coord_sim-2.2.1.dist-info/WHEEL
coord_sim-2.2.1.dist-info/entry_points.txt
coord_sim-2.2.1.dist-info/top_level.txt
coord_sim-2.2.1.dist-info/RECORD
