Metadata-Version: 2.1
Name: coord-sim
Version: 2.2.1
Summary: Simulate flow-level, inter-node network coordination including scaling and placement of services and scheduling/balancing traffic between them.
Home-page: https://github.com/RealVNF/coord-sim
Author: Stefan Schneider
License: MIT
Classifier: Programming Language :: Python :: 3
Classifier: License :: OSI Approved :: MIT License
Classifier: Operating System :: OS Independent
Requires-Python: >=3.6.0
Requires-Dist: simpy (>=4)
Requires-Dist: networkx (==2.4)
Requires-Dist: geopy
Requires-Dist: numpy (<=1.19.5,>=1.16.5)
Requires-Dist: pandas (==1.1.5)
Requires-Dist: matplotlib
Requires-Dist: pyyaml
Provides-Extra: lstm
Requires-Dist: scikit-learn ; extra == 'lstm'
Requires-Dist: keras (==2.2.5) ; extra == 'lstm'
